strip_whitespace/middlewares/HtmlStripWhiteSpaceMiddleware.py
strip_whitespace/middlewares/functions/__init__.py
strip_whitespace/middlewares/functions/add_headers.py
strip_whitespace/middlewares/functions/compress_according_to_algorithm_choice.py
strip_whitespace/middlewares/variables/__init__.py
strip_whitespace/middlewares/variables/compression.py
strip_whitespace/middlewares/variables/ignored_paths.py
strip_whitespace/middlewares/variables/nbsp_mangle_character.py
strip_whitespace/middlewares/variables/python.py
strip_whitespace/middlewares/variables/rust.py
django_strip_whitespace-0.2.3.dist-info/LICENSE
django_strip_whitespace-0.2.3.dist-info/METADATA
django_strip_whitespace-0.2.3.dist-info/WHEEL
django_strip_whitespace-0.2.3.dist-info/top_level.txt
django_strip_whitespace-0.2.3.dist-info/RECORD
